tests/__init__.py
tests/test_solver.py
tests/test_utilities.py
wordle_buddy/__init__.py
wordle_buddy/solver.py
wordle_buddy/utilities.py
wordle_buddy/wordle.py
wordle_buddy/data/allowed_words.txt
wordle_buddy/data/allowed_words_entropies.txt
wordle_buddy/data/possible_words.txt
wordle_buddy/data/possible_words_entropies.txt
wordle_buddy-0.0.4.data/scripts/wordle_buddy
wordle_buddy-0.0.4.data/scripts/wordle_buddy_manual
wordle_buddy-0.0.4.dist-info/LICENSE.rst
wordle_buddy-0.0.4.dist-info/METADATA
wordle_buddy-0.0.4.dist-info/WHEEL
wordle_buddy-0.0.4.dist-info/top_level.txt
wordle_buddy-0.0.4.dist-info/RECORD
