Metadata-Version: 2.1
Name: wordle-buddy
Version: 0.0.4
Summary: A game of wordle with suggested words!
Home-page: https://github.com/ericoden/wordle-buddy
Author: Eric Oden
Author-email: ericjoden94@gmail.com
License: UNKNOWN
Platform: UNKNOWN
Classifier: Programming Language :: Python :: 3
Classifier: License :: OSI Approved :: MIT License
Classifier: Operating System :: OS Independent
Requires-Python: >=3.6
License-File: LICENSE.rst
Requires-Dist: numpy (>=1.21.0)
Requires-Dist: pyglet (==1.5.22)
Requires-Dist: requests (>=2.27.1)
